super_json_normalize/__init__.py
super_json_normalize/super_json_normalize.py
super_json_normalize-0.1.0.dist-info/AUTHORS.md
super_json_normalize-0.1.0.dist-info/LICENSE
super_json_normalize-0.1.0.dist-info/METADATA
super_json_normalize-0.1.0.dist-info/WHEEL
super_json_normalize-0.1.0.dist-info/top_level.txt
super_json_normalize-0.1.0.dist-info/RECORD
