Metadata-Version: 2.1
Name: super_json_normalize
Version: 0.1.0
Summary: A generic, unlimited level json normalizer which unnests and relationalizes arrays at any location. Outputs a normalised set of data which can be imported into a relational table, and pulls in parent keys for joinability
Home-page: https://github.com/AdamRuddGH/super_json_normalize
Author: Adam Rudd
Author-email: Adam@adamrudd.net
License: MIT license
Keywords: super_json_normalize
Platform: UNKNOWN
Classifier: Development Status :: 2 - Pre-Alpha
Classifier: Intended Audience :: Developers
Classifier: License :: OSI Approved :: MIT License
Classifier: Natural Language :: English
Classifier: Programming Language :: Python :: 3
Classifier: Programming Language :: Python :: 3.6
Classifier: Programming Language :: Python :: 3.7
Classifier: Programming Language :: Python :: 3.8
Requires-Python: >=3.6
License-File: LICENSE
License-File: AUTHORS.md
